hun0219_lotto/__init__.py
hun0219_lotto/draw.py
hun0219_lotto-0.1.2.dist-info/METADATA
hun0219_lotto-0.1.2.dist-info/WHEEL
hun0219_lotto-0.1.2.dist-info/top_level.txt
hun0219_lotto-0.1.2.dist-info/RECORD
