Metadata-Version: 2.1
Name: hun0219_lotto
Version: 0.1.2
Summary: Default template for PDM package
Author-email: hun0219 <gsw98000@gmail.com>
License: MIT
Requires-Python: >=3.9
